setup.py
distributions_BR/Binomialdistribution.py
distributions_BR/Gaussiandistribution.py
distributions_BR/Generaldistribution.py
distributions_BR/__init__.py
distributions_BR.egg-info/PKG-INFO
distributions_BR.egg-info/SOURCES.txt
distributions_BR.egg-info/dependency_links.txt
distributions_BR.egg-info/not-zip-safe
distributions_BR.egg-info/top_level.txt