Metadata-Version: 1.0
Name: distributions-BR
Version: 0.1
Summary: Gaussian distributions
Home-page: UNKNOWN
Author: Benjamin Redmond
Author-email: benjamin.redmond1@gmail.com
License: UNKNOWN
Platform: UNKNOWN
